metsim/__init__.py
metsim/_version.py
metsim/constants.py
metsim/datetime.py
metsim/disaggregate.py
metsim/io.py
metsim/metsim.py
metsim/physics.py
metsim/units.py
metsim/cli/__init__.py
metsim/cli/ms.py
metsim/methods/__init__.py
metsim/methods/mtclim.py
metsim/methods/passthrough.py
metsim-2.4.4.dist-info/LICENSE
metsim-2.4.4.dist-info/METADATA
metsim-2.4.4.dist-info/WHEEL
metsim-2.4.4.dist-info/entry_points.txt
metsim-2.4.4.dist-info/top_level.txt
metsim-2.4.4.dist-info/RECORD
