Metadata-Version: 2.1
Name: metsim
Version: 2.4.4
Summary: Meteorology Simulator
Home-page: https://github.com/UW-Hydro/MetSim
Author: Andrew Bennett
Author-email: bennett.andr@gmail.com
Keywords: meteorology,disaggregation,hydrology,climate,mtclim
Requires-Python: >3.6
License-File: LICENSE
Requires-Dist: xarray >=0.11.0
Requires-Dist: numba
Requires-Dist: numpy
Requires-Dist: pandas >=0.25.0
Requires-Dist: dask
Requires-Dist: distributed
Requires-Dist: toolz
Requires-Dist: netCDF4
Requires-Dist: scipy
